pyqdpx/Project.xsd
pyqdpx/__init__.py
pyqdpx/_version.py
pyqdpx/pyqdpx.py
pyqdpx-0.1.8.dist-info/licenses/LICENSE.md
pyqdpx-0.1.8.dist-info/METADATA
pyqdpx-0.1.8.dist-info/WHEEL
pyqdpx-0.1.8.dist-info/top_level.txt
pyqdpx-0.1.8.dist-info/RECORD
