Metadata-Version: 2.4
Name: pyqdpx
Version: 0.1.8
Summary: A Python module to process Qualitative Data Exchange (QDPX) XML files.
Author-email: Pethő Gergely <petho.gergely@etk.unideb.hu>
License-Expression: MIT
Project-URL: Homepage, https://github.com/DEpt-metagenom/pyqdpx
Project-URL: Bug Tracker, https://github.com/DEpt-metagenom/pyqdpx/issues
Classifier: Programming Language :: Python :: 3
Classifier: Operating System :: OS Independent
Requires-Python: >=3.8
License-File: LICENSE.md
Requires-Dist: beautifulsoup4>=4.10.0
Requires-Dist: lxml>=5.3.0
Requires-Dist: regex>=2024.11.6
Dynamic: license-file
